<?xml version="1.0" encoding="UTF-8"?>
<persistence version="2.2"
             xmlns="http://xmlns.jcp.org/xml/ns/persistence"
             xmlns:xsi="http://www.w3.org/2001/XMLSchema-instance"
             xsi:schemaLocation="http://xmlns.jcp.org/xml/ns/persistence
                                 http://xmlns.jcp.org/xml/ns/persistence/persistence_2_2.xsd">
    <persistence-unit name="parkguidancePersistence" transaction-type="JTA">
        <provider>org.hibernate.jpa.HibernatePersistenceProvider</provider>
        <jta-data-source>parkguidanceDataSource</jta-data-source>
        <class>com.neo.parkguidance.framework.entity.ParkingGarage</class>
        <class>com.neo.parkguidance.framework.entity.Address</class>

        

     <properties>
            <property name="javax.persistence.jdbc.driver" value="org.postgresql.Driver"/>
            <property name="hibernate.dialect" value="org.hibernate.dialect.PostgreSQL82Dialect" />
            <property name="hibernate.hbm2ddl.auto" value="update" />
        </properties>
        
    </persistence-unit>
</persistence>